winkerberos.cp314t-win_amd64.pyd
winkerberos-0.13.0.dist-info/licenses/LICENSE
winkerberos-0.13.0.dist-info/METADATA
winkerberos-0.13.0.dist-info/WHEEL
winkerberos-0.13.0.dist-info/top_level.txt
winkerberos-0.13.0.dist-info/RECORD
