Metadata-Version: 2.4
Name: winkerberos
Version: 0.13.0
Summary: High level interface to SSPI for Kerberos client auth
Author-email: Bernie Hackett <bernie@mongodb.com>
License:                                  Apache License
Project-URL: Homepage, https://github.com/mongodb-labs/winkerberos
Keywords: GSSAPI,Kerberos,SSPI
Classifier: Development Status :: 4 - Beta
Classifier: Intended Audience :: Developers
Classifier: License :: OSI Approved :: Apache Software License
Classifier: Operating System :: Microsoft :: Windows
Classifier: Programming Language :: Python :: Implementation :: CPython
Classifier: Programming Language :: Python :: 3
Classifier: Programming Language :: Python :: 3.10
Classifier: Programming Language :: Python :: 3.11
Classifier: Programming Language :: Python :: 3.12
Classifier: Programming Language :: Python :: 3.13
Classifier: Programming Language :: Python :: 3.14
Classifier: Topic :: System :: Systems Administration :: Authentication/Directory
Requires-Python: >=3.10
License-File: LICENSE
Dynamic: license-file
